docker_registry_client/AuthorizationService.py
docker_registry_client/DockerRegistryClient.py
docker_registry_client/Image.py
docker_registry_client/Repository.py
docker_registry_client/_BaseClient.py
docker_registry_client/__init__.py
docker_registry_client/manifest.py
docker_registry_client-0.5.1.dist-info/DESCRIPTION.rst
docker_registry_client-0.5.1.dist-info/METADATA
docker_registry_client-0.5.1.dist-info/RECORD
docker_registry_client-0.5.1.dist-info/WHEEL
docker_registry_client-0.5.1.dist-info/metadata.json
docker_registry_client-0.5.1.dist-info/top_level.txt
