Metadata-Version: 2.0
Name: docker-registry-client
Version: 0.5.1
Summary: Client for Docker Registry V1 and V2
Home-page: https://github.com/yodle/docker-registry-client
Author: John Downs
Author-email: john.downs@yodle.com
License: Apache License 2.0
Keywords: docker docker-registry REST
Platform: UNKNOWN
Classifier: Development Status :: 3 - Alpha
Classifier: Intended Audience :: Developers
Classifier: Topic :: System :: Software Distribution
Classifier: License :: OSI Approved :: Apache Software License
Classifier: Programming Language :: Python :: 2
Classifier: Programming Language :: Python :: 2.7
Classifier: Programming Language :: Python :: 3
Classifier: Programming Language :: Python :: 3.5
Classifier: Programming Language :: Python :: 3.6
Requires-Dist: ecdsa (>=0.13.0,<0.14.0)
Requires-Dist: jws (>=0.1.3,<0.2.0)
Requires-Dist: requests (>=2.4.3,<3.0.0)
